awslabs/__init__.py
awslabs/postgres_mcp_server/__init__.py
awslabs/postgres_mcp_server/mutable_sql_detector.py
awslabs/postgres_mcp_server/server.py
awslabs/postgres_mcp_server/connection/__init__.py
awslabs/postgres_mcp_server/connection/abstract_db_connection.py
awslabs/postgres_mcp_server/connection/cp_api_connection.py
awslabs/postgres_mcp_server/connection/db_connection_map.py
awslabs/postgres_mcp_server/connection/psycopg_pool_connection.py
awslabs/postgres_mcp_server/connection/rds_api_connection.py
awslabs_postgres_mcp_server-1.0.15.dist-info/METADATA
awslabs_postgres_mcp_server-1.0.15.dist-info/WHEEL
awslabs_postgres_mcp_server-1.0.15.dist-info/entry_points.txt
awslabs_postgres_mcp_server-1.0.15.dist-info/licenses/LICENSE
awslabs_postgres_mcp_server-1.0.15.dist-info/licenses/NOTICE
awslabs_postgres_mcp_server-1.0.15.dist-info/RECORD
