Metadata-Version: 2.4
Name: awslabs.postgres-mcp-server
Version: 1.0.15
Summary: An AWS Labs Model Context Protocol (MCP) server for postgres
Project-URL: homepage, https://awslabs.github.io/mcp/
Project-URL: docs, https://awslabs.github.io/mcp/servers/postgres-mcp-server/
Project-URL: documentation, https://awslabs.github.io/mcp/servers/postgres-mcp-server/
Project-URL: repository, https://github.com/awslabs/mcp.git
Project-URL: changelog, https://github.com/awslabs/mcp/blob/main/src/postgres-mcp-server/CHANGELOG.md
Author: Amazon Web Services
Author-email: AWSLabs MCP <203918161+awslabs-mcp@users.noreply.github.com>, Ken Zhang <kennthhz@amazon.com>
License: Apache-2.0
License-File: LICENSE
License-File: NOTICE
Classifier: License :: OSI Approved :: Apache Software License
Classifier: Operating System :: OS Independent
Classifier: Programming Language :: Python
Classifier: Programming Language :: Python :: 3
Classifier: Programming Language :: Python :: 3.10
Classifier: Programming Language :: Python :: 3.11
Classifier: Programming Language :: Python :: 3.12
Classifier: Programming Language :: Python :: 3.13
Requires-Python: >=3.10
Requires-Dist: aiorwlock
Requires-Dist: boto3>=1.42.4
Requires-Dist: botocore>1.42.4
Requires-Dist: loguru>=0.7.0
Requires-Dist: mcp[cli]>=1.23.0
Requires-Dist: psycopg[binary,pool]>=3.1.12
Requires-Dist: pydantic>=2.10.6
